{
  "workflow_run": "380",
  "training_type": ".training-progress/nanecho-cached-ci",
  "completed_at": "2026-04-29T20:08:33.956554",
  "parameters": {
    "max_iters": 500,
    "batch_size": 2,
    "learning_rate": 0.0002,
    "model_layers": 4,
    "model_embedding": 256,
    "force_fresh_start": false
  },
  "cache_stats": {
    "total_checkpoints": 10,
    "total_size_mb": 2509.2101650238037,
    "total_size_gb": 2.4504005517810583,
    "best_quality_score": 998400.7791262518,
    "best_val_loss": 0.003684349216055125,
    "cache_dir": ".training-progress/nanecho-cached-ci/cache"
  },
  "best_checkpoint": {
    "id": "ckpt_20260429_200829_6500_22deff1b_9470fbb7",
    "quality_score": 998400.7791262518,
    "val_loss": 0.003684349216055125,
    "iteration": 6500,
    "created_at": "2026-04-29T20:08:30.094901"
  }
}