{
  "workflow_run": "234",
  "training_type": ".training-progress/nanecho-cached-ci",
  "completed_at": "2026-03-30T08:09:54.408591",
  "parameters": {
    "max_iters": 500,
    "batch_size": 2,
    "learning_rate": 0.0002,
    "model_layers": 4,
    "model_embedding": 256,
    "force_fresh_start": false
  },
  "cache_stats": {
    "total_checkpoints": 10,
    "total_size_mb": 2513.2850551605225,
    "total_size_gb": 2.4543799366801977,
    "best_quality_score": 1152000.780537999,
    "best_val_loss": 0.0017264755500946195,
    "cache_dir": ".training-progress/nanecho-cached-ci/cache"
  },
  "best_checkpoint": {
    "id": "ckpt_20260330_080949_7500_22deff1b_9470fbb7",
    "quality_score": 1152000.780537999,
    "val_loss": 0.0017264755500946195,
    "iteration": 7500,
    "created_at": "2026-03-30T08:09:49.987837"
  }
}