{
  "workflow_run": "466",
  "training_type": ".training-progress/nanecho-cached-ci",
  "completed_at": "2026-05-21T08:58:54.786481",
  "parameters": {
    "max_iters": 500,
    "batch_size": 2,
    "learning_rate": 0.0002,
    "model_layers": 4,
    "model_embedding": 256,
    "force_fresh_start": false
  },
  "cache_stats": {
    "total_checkpoints": 10,
    "total_size_mb": 2515.3225231170654,
    "total_size_gb": 2.456369651481509,
    "best_quality_score": 1228800.7800625213,
    "best_val_loss": 0.0014878135180333629,
    "cache_dir": ".training-progress/nanecho-cached-ci/cache"
  },
  "best_checkpoint": {
    "id": "ckpt_20260521_085850_8000_22deff1b_9470fbb7",
    "quality_score": 1228800.7800625213,
    "val_loss": 0.0014878135180333629,
    "iteration": 8000,
    "created_at": "2026-05-21T08:58:50.781795"
  }
}